omito_config_plugin_aws/__init__.py
omito_config_plugin_aws/conftest.py
omito_config_plugin_aws-0.1.7.dist-info/WHEEL
omito_config_plugin_aws-0.1.7.dist-info/METADATA
omito_config_plugin_aws-0.1.7.dist-info/RECORD
